pysqream_blue_sqlalchemy/__init__.py
pysqream_blue_sqlalchemy/dialect.py
pysqream_blue_sqlalchemy-0.9.3.dist-info/LICENSE
pysqream_blue_sqlalchemy-0.9.3.dist-info/METADATA
pysqream_blue_sqlalchemy-0.9.3.dist-info/WHEEL
pysqream_blue_sqlalchemy-0.9.3.dist-info/entry_points.txt
pysqream_blue_sqlalchemy-0.9.3.dist-info/top_level.txt
pysqream_blue_sqlalchemy-0.9.3.dist-info/RECORD
