Metadata-Version: 2.1
Name: pysqream-blue-sqlalchemy
Version: 0.9.3
Summary: SQLAlchemy dialect for SQream Blue
Home-page: https://github.com/SQream/pysqream_blue_sqlalchemy
Author: SQream
Author-email: info@sqream.com
License: UNKNOWN
Keywords: database sqlalchemy sqream sqreamdb
Platform: UNKNOWN
Classifier: Programming Language :: Python :: 3.9
Classifier: License :: OSI Approved :: BSD License
Classifier: Operating System :: OS Independent
Requires-Python: >=3.9
Requires-Dist: sqlalchemy >=1.3.18
Requires-Dist: pysqream-blue ==1.0.47
Requires-Dist: setuptools >=57.4.0
Requires-Dist: pudb ==2022.1.2
Requires-Dist: pandas ==1.1.5
Requires-Dist: numpy ==1.22.0
Requires-Dist: alembic >=1.6.3
